{
	"00:a3:8e:a4:e3:31": {
		"timestamp": 1519908763.6842632,
		"source": "beacon",
		"bandwith": 20,
		"mac": "00:a3:8e:a4:e3:31",
		"channel": 9,
		"phy_type": 6,
		"ssid": "TUvisitor",
		"b_supported": true,
		"g_supported": true,
		"n_supported": true,
		"data_rate": 24.0,
		"24.0": true,
		"36.0": true,
		"48.0": true,
		"54.0": true,
		"time": "2018-03-01 13:52:43"
	},
	"00:a3:8e:a4:e3:30": {
		"timestamp": 1519908763.7967288,
		"source": "beacon",
		"bandwith": 20,
		"mac": "00:a3:8e:a4:e3:30",
		"channel": 9,
		"phy_type": 6,
		"ssid": "eduroam",
		"b_supported": true,
		"g_supported": true,
		"n_supported": true,
		"data_rate": 24.0,
		"24.0": true,
		"36.0": true,
		"48.0": true,
		"54.0": true,
		"time": "2018-03-01 13:52:43"
	},
	"00:a3:8e:a4:e3:32": {
		"timestamp": 1519908763.8051693,
		"source": "beacon",
		"bandwith": 20,
		"mac": "00:a3:8e:a4:e3:32",
		"channel": 9,
		"phy_type": 6,
		"ssid": "tudelft-dastud",
		"b_supported": true,
		"g_supported": true,
		"n_supported": true,
		"data_rate": 24.0,
		"24.0": true,
		"36.0": true,
		"48.0": true,
		"54.0": true,
		"time": "2018-03-01 13:52:43"
	},
	"00:a3:8e:a4:e9:92": {
		"timestamp": 1519908763.9353619,
		"source": "beacon",
		"bandwith": 20,
		"mac": "00:a3:8e:a4:e9:92",
		"channel": 5,
		"phy_type": 6,
		"ssid": "tudelft-dastud",
		"b_supported": true,
		"g_supported": true,
		"n_supported": true,
		"data_rate": 24.0,
		"24.0": true,
		"36.0": true,
		"48.0": true,
		"54.0": true,
		"time": "2018-03-01 13:52:43"
	},
	"00:a3:8e:a4:e9:91": {
		"timestamp": 1519908763.9845016,
		"source": "beacon",
		"bandwith": 20,
		"mac": "00:a3:8e:a4:e9:91",
		"channel": 5,
		"phy_type": 6,
		"ssid": "TUvisitor",
		"b_supported": true,
		"g_supported": true,
		"n_supported": true,
		"data_rate": 24.0,
		"24.0": true,
		"36.0": true,
		"48.0": true,
		"54.0": true,
		"time": "2018-03-01 13:52:43"
	},
	"00:a3:8e:a4:e9:90": {
		"timestamp": 1519908764.0950468,
		"source": "beacon",
		"bandwith": 20,
		"mac": "00:a3:8e:a4:e9:90",
		"channel": 5,
		"phy_type": 6,
		"ssid": "eduroam",
		"b_supported": true,
		"g_supported": true,
		"n_supported": true,
		"data_rate": 24.0,
		"24.0": true,
		"36.0": true,
		"48.0": true,
		"54.0": true,
		"time": "2018-03-01 13:52:44"
	},
	"00:a3:8e:6c:69:70": {
		"timestamp": 1519908764.542685,
		"source": "beacon",
		"bandwith": 20,
		"mac": "00:a3:8e:6c:69:70",
		"channel": 1,
		"phy_type": 6,
		"ssid": "eduroam",
		"b_supported": true,
		"g_supported": true,
		"n_supported": true,
		"data_rate": 24.0,
		"24.0": true,
		"36.0": true,
		"48.0": true,
		"54.0": true,
		"time": "2018-03-01 13:52:44"
	},
	"00:a3:8e:6c:69:72": {
		"timestamp": 1519908764.593342,
		"source": "beacon",
		"bandwith": 20,
		"mac": "00:a3:8e:6c:69:72",
		"channel": 1,
		"phy_type": 6,
		"ssid": "tudelft-dastud",
		"b_supported": true,
		"g_supported": true,
		"n_supported": true,
		"data_rate": 24.0,
		"24.0": true,
		"36.0": true,
		"48.0": true,
		"54.0": true,
		"time": "2018-03-01 13:52:44"
	},
	"00:a3:8e:6c:69:71": {
		"timestamp": 1519908764.6409767,
		"source": "beacon",
		"bandwith": 20,
		"mac": "00:a3:8e:6c:69:71",
		"channel": 1,
		"phy_type": 6,
		"ssid": "TUvisitor",
		"b_supported": true,
		"g_supported": true,
		"n_supported": true,
		"data_rate": 24.0,
		"24.0": true,
		"36.0": true,
		"48.0": true,
		"54.0": true,
		"time": "2018-03-01 13:52:44"
	},
	"00:a3:8e:6c:65:62": {
		"timestamp": 1519908764.7643132,
		"source": "beacon",
		"bandwith": 20,
		"mac": "00:a3:8e:6c:65:62",
		"channel": 13,
		"phy_type": 6,
		"ssid": "tudelft-dastud",
		"b_supported": true,
		"g_supported": true,
		"n_supported": true,
		"data_rate": 24.0,
		"24.0": true,
		"36.0": true,
		"48.0": true,
		"54.0": true,
		"time": "2018-03-01 13:52:44"
	},
	"00:a3:8e:6c:65:61": {
		"timestamp": 1519908764.8133738,
		"source": "beacon",
		"bandwith": 20,
		"mac": "00:a3:8e:6c:65:61",
		"channel": 13,
		"phy_type": 6,
		"ssid": "TUvisitor",
		"b_supported": true,
		"g_supported": true,
		"n_supported": true,
		"data_rate": 24.0,
		"24.0": true,
		"36.0": true,
		"48.0": true,
		"54.0": true,
		"time": "2018-03-01 13:52:44"
	},
	"00:a3:8e:6c:65:60": {
		"timestamp": 1519908764.8949642,
		"source": "beacon",
		"bandwith": 20,
		"mac": "00:a3:8e:6c:65:60",
		"channel": 13,
		"phy_type": 6,
		"ssid": "eduroam",
		"b_supported": true,
		"g_supported": true,
		"n_supported": true,
		"data_rate": 24.0,
		"24.0": true,
		"36.0": true,
		"48.0": true,
		"54.0": true,
		"time": "2018-03-01 13:52:44"
	},
	"30:b5:c2:c4:5f:b0": {
		"timestamp": 1519908765.0490355,
		"source": "beacon",
		"bandwith": 40,
		"mac": "30:b5:c2:c4:5f:b0",
		"channel": 6,
		"phy_type": 4,
		"ssid": "TP-LINK_C45FB0",
		"b_supported": true,
		"g_supported": true,
		"n_supported": true,
		"data_rate": 1.0,
		"1.0": true,
		"2.0": true,
		"5.5": true,
		"11.0": true,
		"6.0": true,
		"9.0": true,
		"12.0": true,
		"18.0": true,
		"24.0": true,
		"36.0": true,
		"48.0": true,
		"54.0": true,
		"time": "2018-03-01 13:52:45"
	},
	"90:f6:52:3e:3d:8a": {
		"timestamp": 1519908765.4816954,
		"source": "beacon",
		"bandwith": 20,
		"mac": "90:f6:52:3e:3d:8a",
		"channel": 11,
		"phy_type": 4,
		"ssid": "TEMPORARY",
		"b_supported": true,
		"g_supported": true,
		"n_supported": true,
		"data_rate": 1.0,
		"1.0": true,
		"2.0": true,
		"5.5": true,
		"11.0": true,
		"6.0": true,
		"9.0": true,
		"12.0": true,
		"18.0": true,
		"24.0": true,
		"36.0": true,
		"48.0": true,
		"54.0": true,
		"time": "2018-03-01 13:52:45"
	},
	"92:f6:52:3e:3d:8a": {
		"timestamp": 1519908765.494497,
		"source": "beacon",
		"bandwith": 20,
		"mac": "92:f6:52:3e:3d:8a",
		"channel": 11,
		"phy_type": 4,
		"ssid": "TEMPORARY2",
		"b_supported": true,
		"g_supported": true,
		"n_supported": true,
		"data_rate": 1.0,
		"1.0": true,
		"2.0": true,
		"5.5": true,
		"11.0": true,
		"6.0": true,
		"9.0": true,
		"12.0": true,
		"18.0": true,
		"24.0": true,
		"36.0": true,
		"48.0": true,
		"54.0": true,
		"time": "2018-03-01 13:52:45"
	},
	"00:0c:f6:d8:a1:e8": {
		"timestamp": 1519908765.5464416,
		"source": "beacon",
		"bandwith": 40,
		"mac": "00:0c:f6:d8:a1:e8",
		"channel": 11,
		"phy_type": 4,
		"ssid": "SitecomD8A1E8",
		"b_supported": true,
		"g_supported": true,
		"n_supported": true,
		"data_rate": 1.0,
		"1.0": true,
		"2.0": true,
		"5.5": true,
		"11.0": true,
		"9.0": true,
		"18.0": true,
		"36.0": true,
		"54.0": true,
		"6.0": true,
		"12.0": true,
		"24.0": true,
		"48.0": true,
		"time": "2018-03-01 13:52:45"
	},
	"78:54:2e:fd:e3:80": {
		"timestamp": 1519908779.1330032,
		"source": "beacon",
		"bandwith": 40,
		"mac": "78:54:2e:fd:e3:80",
		"channel": 1,
		"phy_type": 4,
		"ssid": "IreneDaBohmba",
		"b_supported": true,
		"g_supported": true,
		"n_supported": true,
		"data_rate": 1.0,
		"1.0": true,
		"2.0": true,
		"5.5": true,
		"11.0": true,
		"9.0": true,
		"18.0": true,
		"36.0": true,
		"54.0": true,
		"6.0": true,
		"12.0": true,
		"24.0": true,
		"48.0": true,
		"time": "2018-03-01 13:52:59"
	},
	"00:a3:8e:a4:e8:01": {
		"timestamp": 1519908792.8639383,
		"source": "beacon",
		"bandwith": 20,
		"mac": "00:a3:8e:a4:e8:01",
		"channel": 9,
		"phy_type": 6,
		"ssid": "TUvisitor",
		"b_supported": true,
		"g_supported": true,
		"n_supported": true,
		"data_rate": 24.0,
		"24.0": true,
		"36.0": true,
		"48.0": true,
		"54.0": true,
		"time": "2018-03-01 13:53:12"
	},
	"00:a3:8e:a4:e8:02": {
		"timestamp": 1519908792.8828683,
		"source": "beacon",
		"bandwith": 20,
		"mac": "00:a3:8e:a4:e8:02",
		"channel": 9,
		"phy_type": 6,
		"ssid": "tudelft-dastud",
		"b_supported": true,
		"g_supported": true,
		"n_supported": true,
		"data_rate": 24.0,
		"24.0": true,
		"36.0": true,
		"48.0": true,
		"54.0": true,
		"time": "2018-03-01 13:53:12"
	},
	"00:a3:8e:a4:e8:00": {
		"timestamp": 1519908796.6502712,
		"source": "beacon",
		"bandwith": 20,
		"mac": "00:a3:8e:a4:e8:00",
		"channel": 9,
		"phy_type": 6,
		"ssid": "eduroam",
		"b_supported": true,
		"g_supported": true,
		"n_supported": true,
		"data_rate": 24.0,
		"24.0": true,
		"36.0": true,
		"48.0": true,
		"54.0": true,
		"time": "2018-03-01 13:53:16"
	},
	"a0:63:91:05:e0:38": {
		"timestamp": 1519908799.930298,
		"source": "beacon",
		"bandwith": 20,
		"mac": "a0:63:91:05:e0:38",
		"channel": 4,
		"phy_type": 4,
		"ssid": "bike",
		"b_supported": true,
		"g_supported": true,
		"n_supported": true,
		"data_rate": 1.0,
		"1.0": true,
		"2.0": true,
		"5.5": true,
		"11.0": true,
		"9.0": true,
		"18.0": true,
		"36.0": true,
		"54.0": true,
		"6.0": true,
		"12.0": true,
		"24.0": true,
		"48.0": true,
		"time": "2018-03-01 13:53:19"
	},
	"32:b5:c2:c4:6f:44": {
		"timestamp": 1519908805.425196,
		"source": "beacon",
		"bandwith": 20,
		"mac": "32:b5:c2:c4:6f:44",
		"channel": 11,
		"phy_type": 4,
		"ssid": "Please wait...",
		"b_supported": true,
		"g_supported": true,
		"n_supported": true,
		"data_rate": 1.0,
		"1.0": true,
		"2.0": true,
		"5.5": true,
		"11.0": true,
		"6.0": true,
		"9.0": true,
		"12.0": true,
		"18.0": true,
		"24.0": true,
		"36.0": true,
		"48.0": true,
		"54.0": true,
		"time": "2018-03-01 13:53:25"
	},
	"30:b5:c2:c4:6f:44": {
		"timestamp": 1519908805.5149734,
		"source": "beacon",
		"bandwith": 20,
		"mac": "30:b5:c2:c4:6f:44",
		"channel": 11,
		"phy_type": 4,
		"ssid": "SORRY",
		"b_supported": true,
		"g_supported": true,
		"n_supported": true,
		"data_rate": 1.0,
		"1.0": true,
		"2.0": true,
		"5.5": true,
		"11.0": true,
		"6.0": true,
		"9.0": true,
		"12.0": true,
		"18.0": true,
		"24.0": true,
		"36.0": true,
		"48.0": true,
		"54.0": true,
		"time": "2018-03-01 13:53:25"
	},
	"2c:33:11:31:da:a0": {
		"timestamp": 1519908844.7911546,
		"source": "beacon",
		"bandwith": 20,
		"mac": "2c:33:11:31:da:a0",
		"channel": 1,
		"phy_type": 6,
		"ssid": "eduroam",
		"b_supported": true,
		"g_supported": true,
		"n_supported": true,
		"data_rate": 24.0,
		"24.0": true,
		"36.0": true,
		"48.0": true,
		"54.0": true,
		"time": "2018-03-01 13:54:04"
	},
	"2c:33:11:31:da:a2": {
		"timestamp": 1519908852.0690768,
		"source": "beacon",
		"bandwith": 20,
		"mac": "2c:33:11:31:da:a2",
		"channel": 1,
		"phy_type": 6,
		"ssid": "tudelft-dastud",
		"b_supported": true,
		"g_supported": true,
		"n_supported": true,
		"data_rate": 24.0,
		"24.0": true,
		"36.0": true,
		"48.0": true,
		"54.0": true,
		"time": "2018-03-01 13:54:12"
	},
	"2c:33:11:31:da:a1": {
		"timestamp": 1519908859.4399722,
		"source": "beacon",
		"bandwith": 20,
		"mac": "2c:33:11:31:da:a1",
		"channel": 1,
		"phy_type": 6,
		"ssid": "TUvisitor",
		"b_supported": true,
		"g_supported": true,
		"n_supported": true,
		"data_rate": 24.0,
		"24.0": true,
		"36.0": true,
		"48.0": true,
		"54.0": true,
		"time": "2018-03-01 13:54:19"
	}
}